mcp_manager/__init__.py
mcp_manager/analytics.py
mcp_manager/app_manager.py
mcp_manager/cli.py
mcp_manager/client_integration.py
mcp_manager/config_manager.py
mcp_manager/configuration_handler.py
mcp_manager/env_manager.py
mcp_manager/package.py
mcp_manager/runtime_utils.py
tests/__init__.py
tests/test_package.py
omcp_manager-0.1.0.dist-info/METADATA
omcp_manager-0.1.0.dist-info/WHEEL
omcp_manager-0.1.0.dist-info/entry_points.txt
omcp_manager-0.1.0.dist-info/top_level.txt
omcp_manager-0.1.0.dist-info/RECORD
