Metadata-Version: 2.4
Name: omcp-manager
Version: 0.1.0
Summary: OMCP 管理器：用于管理模型上下文协议（MCP）服务器的包管理器
Home-page: https://github.com/jinyalong/omcp
Author: 金亚龙
Author-email: jinyalong.jyl@antgroup.com
Classifier: Programming Language :: Python :: 3
Classifier: License :: OSI Approved :: MIT License
Classifier: Operating System :: OS Independent
Requires-Python: >=3.7
Requires-Dist: rich
Requires-Dist: typer
Dynamic: author
Dynamic: author-email
Dynamic: classifier
Dynamic: description
Dynamic: description-content-type
Dynamic: home-page
Dynamic: requires-dist
Dynamic: requires-python
Dynamic: summary
